{  
   "campaignsPresent":true,
   "showSSC":false,
   "serviceCampaigns":[  
      {  
         "campaignComplete":true,
         "campaignDescr":"Completed",
         "campaignTitle":"Safety Recall D0B Remedy Notice - 2003 through 2004 Model Year Corolla and Corolla Matrix Vehicles - Supplemental Restraint System (SRS) Electronic Control Module (ECM)",
         "completionCode":"00",
         "dateOfService":"04/20/13",
         "dealerCode":"04487",
         "dealerName":"TOYOTA VACAVILLE ",
         "detailMemo":null,
         "detailMemoEmpty":true,
         "documentListEmpty":false,
         "rowIndex":"0",
         "t3DocumentList":[  
            {  
               "documentUrl":"/t3Portal/resources/jsp/siviewer/index.jsp?href=cp/T-CP-D0B-A110-D/xhtml/T-CP-D0B-A110-D.html&locale=en",
               "language":"en",
               "objectTitle":"Safety Recall D0B: 2003-2004 Corolla and Corolla Matrix; Supplemental Restraint System (SRS) Electronic Control Module (ECM) (Dealer Letter)",
               "objectType":"cp",
               "publicationNumber":"T-CP-D0B-A110-D",
               "t3Id":"T-CP-D0B-A110-D",
               "encodeObjectTitle":null,
               "summary":null,
               "docId":null,
               "rowIndex":null,
               "titleMSG":null,
               "addToFav":null,
               "rateDocument":null,
               "contentCorrection":null
            },
            {  
               "documentUrl":"/t3Portal/resources/jsp/siviewer/index.jsp?href=cp/T-CP-D0B-A520-D/xhtml/T-CP-D0B-A520-D.html&locale=en",
               "language":"en",
               "objectTitle":"Safety Recall D0B: 2003-2004 Matrix; Supplemental Restraint System (SRS) Electronic Control Module (ECM) (Technical Instructions)",
               "objectType":"cp",
               "publicationNumber":"T-CP-D0B-A520-D",
               "t3Id":"T-CP-D0B-A520-D",
               "encodeObjectTitle":null,
               "summary":null,
               "docId":null,
               "rowIndex":null,
               "titleMSG":null,
               "addToFav":null,
               "rateDocument":null,
               "contentCorrection":null
            }
         ]
      },
      {  
         "campaignComplete":true,
         "campaignDescr":"Completed",
         "campaignTitle":"Safety Recall 80A - 2003 Through 2004 Model Corolla and Corolla Matrix Front Door Glass Bolts",
         "completionCode":"00",
         "dateOfService":"07/27/09",
         "dealerCode":"04487",
         "dealerName":"TOYOTA VACAVILLE ",
         "detailMemo":null,
         "detailMemoEmpty":true,
         "documentListEmpty":false,
         "rowIndex":"1",
         "t3DocumentList":[  
            {  
               "documentUrl":"/t3Portal/resources/jsp/siviewer/index.jsp?href=cp/T-CP-80A-0001-W/xhtml/T-CP-80A-0001-W.html&locale=en",
               "language":"en",
               "objectTitle":"SSC 80A - Certain 2003 Through 2004 Model Year Corolla And Corolla Matrix - Front Door Glass Bolts",
               "objectType":"cp",
               "publicationNumber":"T-CP-80A-0001-W",
               "t3Id":"T-CP-80A-0001-W",
               "encodeObjectTitle":null,
               "summary":null,
               "docId":null,
               "rowIndex":null,
               "titleMSG":null,
               "addToFav":null,
               "rateDocument":null,
               "contentCorrection":null
            }
         ]
      }
   ]
}